streamlit_typst/__init__.py
streamlit_typst/frontend/out/404.html
streamlit_typst/frontend/out/_next/static/BN0pkrWK3ydA0BPmYGysN/_buildManifest.js
streamlit_typst/frontend/out/_next/static/BN0pkrWK3ydA0BPmYGysN/_ssgManifest.js
streamlit_typst/frontend/out/_next/static/chunks/268.f56718ff25378b03.js
streamlit_typst/frontend/out/_next/static/chunks/401.8e4b53f6e5f84db4.js
streamlit_typst/frontend/out/_next/static/chunks/630.c53c75e245834ef5.js
streamlit_typst/frontend/out/_next/static/chunks/807-accefa5a4e6cb931.js
streamlit_typst/frontend/out/_next/static/chunks/807-accefa5a4e6cb931.js.LICENSE.txt
streamlit_typst/frontend/out/_next/static/chunks/framework-32d5e86448f8df8d.js
streamlit_typst/frontend/out/_next/static/chunks/framework-32d5e86448f8df8d.js.LICENSE.txt
streamlit_typst/frontend/out/_next/static/chunks/main-983bf68dc6814303.js
streamlit_typst/frontend/out/_next/static/chunks/pages/_app-57d89f3406606de9.js
streamlit_typst/frontend/out/_next/static/chunks/pages/_error-7f1f326cc5f96728.js
streamlit_typst/frontend/out/_next/static/chunks/pages/index-ed3ee15f4e49330b.js
streamlit_typst/frontend/out/_next/static/chunks/polyfills-78c92fac7aa8fdd8.js
streamlit_typst/frontend/out/_next/static/chunks/webpack-c92235cd74224e0f.js
streamlit_typst/frontend/out/_next/static/css/5c6253b39f0973c0.css
streamlit_typst/frontend/out/favicon.ico
streamlit_typst/frontend/out/index.html
streamlit_typst/frontend/out/typst_ts_renderer_bg.wasm
streamlit_typst/frontend/out/typst_ts_web_compiler_bg.wasm
streamlit_typst/frontend/out/vercel.svg
streamlit_typst/st_hack.py
streamlit_typst-1.0.5.dist-info/LICENSE
streamlit_typst-1.0.5.dist-info/METADATA
streamlit_typst-1.0.5.dist-info/WHEEL
streamlit_typst-1.0.5.dist-info/RECORD
